etc/ursa-major/ursa-major-stage.conf
etc/ursa-major/ursa-major.conf
ursa_major/__init__.py
ursa_major/cli.py
ursa_major/koji_service.py
ursa_major/logger.py
ursa_major/mail.py
ursa_major/mbs.py
ursa_major/utils.py
ursa_major/handlers/__init__.py
ursa_major/handlers/add_module.py
ursa_major/handlers/add_tag.py
ursa_major/handlers/base.py
ursa_major/handlers/check_config.py
ursa_major/handlers/remove_module.py
ursa_major/handlers/show_config.py
ursa_major/templates/mail/add-tag-error.txt.j2
ursa_major/templates/mail/add-tag.txt.j2
ursa_major/templates/mail/base.txt.j2
ursa_major-0.1.1.dist-info/METADATA
ursa_major-0.1.1.dist-info/RECORD
ursa_major-0.1.1.dist-info/WHEEL
ursa_major-0.1.1.dist-info/entry_points.txt
ursa_major-0.1.1.dist-info/top_level.txt
