Metadata-Version: 2.1
Name: ursa-major
Version: 0.1.1
Summary: A utility for managing module tags in koji's tag inheritance
Home-page: https://pagure.io/ursa-major/
Author: The Factory 2.0 Team
Author-email: ursa-major-owner@fedoraproject.org
License: MIT
Keywords: ursa-major modularity koji fedora
Platform: UNKNOWN
Classifier: Programming Language :: Python
Classifier: Topic :: Utilities
Requires-Dist: koji
Requires-Dist: pygobject
Requires-Dist: pycairo
Requires-Dist: requests
Requires-Dist: jinja2
Requires-Dist: futures; python_version < "3"
